__init__.py
CEval/__init__.py
CEval-0.0.6.dist-info/LICENSE
CEval-0.0.6.dist-info/METADATA
CEval-0.0.6.dist-info/WHEEL
CEval-0.0.6.dist-info/top_level.txt
CEval-0.0.6.dist-info/RECORD
