Metadata-Version: 2.1
Name: CEval
Version: 0.0.6
Summary: A package for evaluating the performance of counterfactual explainers.
Author-email: Betül Bayrak <betul.bayrak@ntnu.no>
Classifier: Programming Language :: Python :: 3
Classifier: License :: OSI Approved :: MIT License
Classifier: Operating System :: OS Independent
Requires-Python: >=3.9
License-File: LICENSE
Requires-Dist: gower >=0.1.2
Requires-Dist: category-encoders >=2.6.3
